killpy/__init__.py
killpy/__main__.py
killpy/cli.py
killpy/cleaners/__init__.py
killpy/commands/__init__.py
killpy/commands/clean.py
killpy/files/__init__.py
killpy/killers/__init__.py
killpy/killers/conda_killer.py
killpy/killers/killer.py
killpy/killers/pipx_killer.py
killpy/killers/poetry_killer.py
killpy/killers/pyenv_killer.py
killpy/killers/venv_killer.py
killpy-0.15.4.dist-info/METADATA
killpy-0.15.4.dist-info/WHEEL
killpy-0.15.4.dist-info/entry_points.txt
killpy-0.15.4.dist-info/top_level.txt
killpy-0.15.4.dist-info/RECORD
