Metadata-Version: 2.2
Name: killpy
Version: 0.15.4
Summary: List all .venv directories and Conda environments 🐍 on your system and check how much space they are using. You can then choose which ones to delete in order to free up space 🧹.
Classifier: Environment :: Console
Classifier: License :: OSI Approved :: MIT License
Classifier: Programming Language :: Python :: 3.12
Requires-Python: >=3.12
Requires-Dist: click>=8.1.8
Requires-Dist: rich>=13.9.4
Requires-Dist: textual>=1.0.0
